model_mocker-0.1.1.dist-info/METADATA
model_mocker-0.1.1.dist-info/WHEEL
model_mocker-0.1.1.dist-info/entry_points.txt
model_mocker-0.1.1.dist-info/licenses/LICENCE
model_mocker/__init__.py
model_mocker/core.py
model_mocker/main.py
model_mocker/providers/bool_provider.py
model_mocker/providers/date_provider.py
model_mocker/providers/number_provider.py
model_mocker/providers/payment_provider.py
model_mocker/providers/string_provider.py
model_mocker-0.1.1.dist-info/RECORD
