Metadata-Version: 2.1
Name: model-mocker
Version: 0.1.1
Summary: Default template for PDM package
Author-Email: Paul <paulotto.bethge@gmail.com>
License: MIT
Requires-Python: >=3.9
Requires-Dist: pydantic>=2.11.3
Requires-Dist: pytest>=8.3.5
Requires-Dist: Faker>=37.1.0
Requires-Dist: pytest-asyncio>=0.26.0
Requires-Dist: twine>=6.1.0
